tasks/__init__.py
tasks/get_task_history.py
tasks/get_tasks.py
test/__init__.py
test/test_get_task_history.py
test/test_get_tasks.py
mod_taiga-0.1.3.dist-info/METADATA
mod_taiga-0.1.3.dist-info/WHEEL
mod_taiga-0.1.3.dist-info/top_level.txt
mod_taiga-0.1.3.dist-info/RECORD
