Metadata-Version: 2.1
Name: mod-taiga
Version: 0.1.3
Summary: Taiga Library
Author: shikhaverma
